calculateur_taux_imposition_qc/__init__.py
calculateur_taux_imposition_qc/calculateur.py
calculateur_taux_imposition_qc/tax_brackets.csv
tests/__init__.py
tests/test_taux_imposition_qc.py
calculateur_taux_imposition_qc-2025.4.dist-info/LICENSE
calculateur_taux_imposition_qc-2025.4.dist-info/METADATA
calculateur_taux_imposition_qc-2025.4.dist-info/WHEEL
calculateur_taux_imposition_qc-2025.4.dist-info/top_level.txt
calculateur_taux_imposition_qc-2025.4.dist-info/RECORD
