Metadata-Version: 2.2
Name: calculateur_taux_imposition_qc
Version: 2025.4
Summary: Calculateur de taux d'imposition pour particuliers pour le Québec
Author: Samuel Paquette-Paré
Author-email: Samuel Paquette-Paré <paquetteparesamuel@gmail.com>
Maintainer-email: Samuel Paquette-Paré <paquetteparesamuel@gmail.com>
License: MIT License
Project-URL: Repository, https://github.com/samuelpaquette-pare/calculateur_taux_imposition_qc.git
Project-URL: Issues, https://github.com/samuelpaquette-pare/calculateur_taux_imposition_qc/issues
Classifier: Programming Language :: Python :: 3
Classifier: License :: OSI Approved :: MIT License
Classifier: Operating System :: OS Independent
Requires-Python: >=3.8
License-File: LICENSE
Dynamic: author
